README.rst
setup.cfg
setup.py
wtforms_geo/__init__.py
wtforms_geo/fields.py
wtforms_geo/widgets.py
wtforms_geo.egg-info/PKG-INFO
wtforms_geo.egg-info/SOURCES.txt
wtforms_geo.egg-info/dependency_links.txt
wtforms_geo.egg-info/not-zip-safe
wtforms_geo.egg-info/pbr.json
wtforms_geo.egg-info/requires.txt
wtforms_geo.egg-info/top_level.txt