Metadata-Version: 1.1
Name: wtforms-geo
Version: 0.0.3
Summary: WTForms geojson fields and widgets.
Home-page: https://github.com/ecarrara/wtforms-geo
Author: Erle Carrara
Author-email: carrara.erle@gmail.com
License: BSD
Keywords: form geo gis
Platform: any
Classifier: Development Status :: 3 - Alpha
Classifier: Intended Audience :: Developers
Classifier: Environment :: Web Environment
Classifier: License :: OSI Approved :: BSD License
Classifier: Operating System :: OS Independent
Classifier: Programming Language :: Python :: 2
Classifier: Programming Language :: Python :: 3
